lunsformter-0.1.2.dist-info/licenses/LICENSE
lunsft/__init__.py
lunsft/lunsformter.py
lunsft/lunslib.py
lunsformter-0.1.2.dist-info/METADATA
lunsformter-0.1.2.dist-info/WHEEL
lunsformter-0.1.2.dist-info/top_level.txt
lunsformter-0.1.2.dist-info/RECORD
