Metadata-Version: 2.4
Name: lunsformter
Version: 0.1.2
Summary: A lightweight, flexible transformer-like language model toolkit with inside-out generation.
Home-page: https://github.com/yourusername/lunsformter
Author: Your Name
Author-email: youremail@example.com
License: MIT
Keywords: transformer language-model NLP BPE inside-out generation research
Classifier: Programming Language :: Python :: 3
Classifier: License :: OSI Approved :: MIT License
Classifier: Intended Audience :: Science/Research
Classifier: Topic :: Scientific/Engineering :: Artificial Intelligence
Requires-Python: >=3.6
License-File: LICENSE
Requires-Dist: numpy
Requires-Dist: torch
Dynamic: author
Dynamic: author-email
Dynamic: classifier
Dynamic: home-page
Dynamic: keywords
Dynamic: license
Dynamic: license-file
Dynamic: requires-dist
Dynamic: requires-python
Dynamic: summary
